{
  "data": [
    { "log_id": 2, "tag_id": 2, "uid": 2, "status": 1 },
    { "log_id": 4, "tag_id": 3, "uid": 2, "status": 1 },
    { "log_id": 5, "tag_id": 4, "uid": 2, "status": 1 },
    { "log_id": 6, "tag_id": 1, "uid": 2, "status": 0 },
    { "log_id": 12, "tag_id": 5, "uid": 2, "status": 0 },
    { "log_id": 17, "tag_id": 14, "uid": 2, "status": 1 }
  ],
  "rows": 6,
  "dates": [],
  "ip": "10.8.60.203",
  "header": ["log_id", "tag_id", "uid", "status"],
  "title": "查询指定专家的标签列表",
  "time": "19.708ms",
  "serverTime": "2021-06-17 17:10:11",
  "source": "数据来源：接口管理",
  "hash": "W/\"b00e094e0465411057efbe7858b0583e\""
}
